fcollections/core/__init__.py
fcollections/core/_codecs.py
fcollections/core/_filenames.py
fcollections/core/_filesdb.py
fcollections/core/_listing.py
fcollections/core/_metadata.py
fcollections/core/_mixins.py
fcollections/core/_readers.py
fcollections/core/_testers.py
fcollections/core/assets/style.css
fcollections/core/assets/template.jinja
fcollections/geometry/__init__.py
fcollections/geometry/_box.py
fcollections/geometry/_distances.py
fcollections/geometry/_extraction.py
fcollections/geometry/_model.py
fcollections/geometry/_search.py
fcollections/geometry/_track_orientation.py
fcollections/implementations/__init__.py
fcollections/implementations/_dac.py
fcollections/implementations/_definitions.py
fcollections/implementations/_era5.py
fcollections/implementations/_gridded_sla.py
fcollections/implementations/_l2_lr_ssh.py
fcollections/implementations/_l2_nadir.py
fcollections/implementations/_l3_lr_ssh.py
fcollections/implementations/_l3_lr_ww.py
fcollections/implementations/_l3_nadir.py
fcollections/implementations/_mur.py
fcollections/implementations/_ocean_color.py
fcollections/implementations/_ohc.py
fcollections/implementations/_readers.py
fcollections/implementations/_s1aowi.py
fcollections/implementations/_sst.py
fcollections/implementations/_swh.py
fcollections/implementations/optional/__init__.py
fcollections/implementations/optional/_area_selectors.py
fcollections/implementations/optional/_model.py
fcollections/implementations/optional/_predicates.py
fcollections/implementations/optional/_reader.py
fcollections/missions/__init__.py
fcollections/missions/_phases.py
fcollections/sad/__init__.py
fcollections/sad/_gshhg.py
fcollections/sad/_interface.py
fcollections/sad/_karin.py
fcollections/time/__init__.py
fcollections/time/_conversions.py
fcollections/time/_operations.py
fcollections/time/_periods.py
fcollections/utilities/constants.py
fcollections/utilities/reshape.py
files_collections-0.1.3.dist-info/licenses/LICENCE
files_collections-0.1.3.dist-info/METADATA
files_collections-0.1.3.dist-info/WHEEL
files_collections-0.1.3.dist-info/entry_points.txt
files_collections-0.1.3.dist-info/top_level.txt
files_collections-0.1.3.dist-info/RECORD
